{
  "category": "【專業級】-第六類：物聯網感知層協定與技術",
  "questions": [
    {
      "id": 1,
      "question": "目前我國政府經濟部商業司主要推廣下列哪一種二維條碼？",
      "options": {
        "A": "PDF417",
        "B": "Datamatrix",
        "C": "Maxicode",
        "D": "Code1"
      },
      "answers": ["A"]
    },
    {
      "id": 2,
      "question": "下列哪一種微處理器是同時將 CPU、Flash ROM、RAM、I/O、A/D、D/A 等相關運算與記憶體及周邊界面整合在一起？",
      "options": {
        "A": "特殊應用積體電路（ASIC）",
        "B": "數位訊號處理器（DSP）",
        "C": "現場可程式化邏輯閘陣列（FPGA）",
        "D": "微控制器（MCU）"
      },
      "answers": ["D"]
    },
    {
      "id": 3,
      "question": "為了縮短感測器的開發時程，並降低微處理器的重新設計成本，下列哪一種微處理器比較適合用於產品開發時可能不斷變更設計的電路系統？",
      "options": {
        "A": "特殊應用積體電路（ASIC）",
        "B": "數位訊號處理器（DSP）",
        "C": "現場可程式化邏輯閘陣列（FPGA）",
        "D": "微控制器（MCU）"
      },
      "answers": ["C"]
    },
    {
      "id": 4,
      "question": "下列哪一種感測器可以感知磁場方向，故具有簡易辨別方向的能力？",
      "options": {
        "A": "電子羅盤",
        "B": "陀螺儀",
        "C": "移動偵測器",
        "D": "震動感測器"
      },
      "answers": ["A"]
    },
    {
      "id": 5,
      "question": "智慧型感測器通常使用下列哪一種電源模組，因其擁有較高電容量，且具有較低記憶效應以及低環境污染等特性？",
      "options": {
        "A": "鎳氫電池",
        "B": "水銀電池",
        "C": "鉛酸電池",
        "D": "太陽能電池"
      },
      "answers": ["A"]
    },
    {
      "id": 6,
      "question": "物聯網的感知層中除了感知、辨識的功用之外，下列哪些功用也包含在內？",
      "options": {
        "A": "定位",
        "B": "通訊",
        "C": "服務",
        "D": "應用"
      },
      "answers": ["A", "B"]
    },
    {
      "id": 7,
      "question": "歐洲商品條碼（EAN）為防止讀取資料錯誤情形發生，必須有一檢查碼，它位於歐洲商品條碼（EAN）中的哪一個位置？",
      "options": {
        "A": "最右邊",
        "B": "最左邊",
        "C": "中間",
        "D": "上面"
      },
      "answers": ["A"]
    },
    {
      "id": 8,
      "question": "NFC 裝置依照角色不同而具備不同的基本溝通模式，下列哪些模式包含在內？",
      "options": {
        "A": "讀取/寫入模式（Reader/writer mode）",
        "B": "卡片模擬模式（Card emulation mode）",
        "C": "點對點模式（Peer-to-Peer mode）",
        "D": "面對面模式（Face-to-Face mode）"
      },
      "answers": ["A", "B", "C"]
    },
    {
      "id": 9,
      "question": "NFC 在主動模式下，最大資料傳輸量應為下列哪一項？",
      "options": {
        "A": "106Kbps",
        "B": "212Kbps",
        "C": "424Kbps",
        "D": "846Kbps"
      },
      "answers": ["C"]
    },
    {
      "id": 10,
      "question": "關於 NFC，下列敘述哪些正確？",
      "options": {
        "A": "短距離高頻無線通訊",
        "B": "短距離低頻寬",
        "C": "短距離高頻寬",
        "D": "短距離低頻無線通訊"
      },
      "answers": ["A", "B"]
    },
    {
      "id": 11,
      "question": "下列哪一種記憶體較適合存放感測器電路系統中，所探測到的數據？",
      "options": {
        "A": "RAM",
        "B": "Flash",
        "C": "ROM",
        "D": "Disk"
      },
      "answers": ["A"]
    },
    {
      "id": 12,
      "question": "二維條碼依其結構可分為下列哪兩大類型？",
      "options": {
        "A": "堆疊式",
        "B": "矩陣式",
        "C": "點陣式",
        "D": "混合式"
      },
      "answers": ["A", "B"]
    },
    {
      "id": 13,
      "question": "下列哪些是常見於智慧型感測器的電源模組？",
      "options": {
        "A": "鎳氫電池",
        "B": "鋰電池",
        "C": "太陽能電池",
        "D": "鉛酸電池"
      },
      "answers": ["A", "B", "C"]
    },
    {
      "id": 14,
      "question": "在台灣若有新書出版或新期刊創立應向下列哪一個機關申請 ISBN 與 ISSN 代碼？",
      "options": {
        "A": "國家圖書館",
        "B": "中央研究院",
        "C": "台北市立圖書館",
        "D": "中華民國商品條碼策進會"
      },
      "answers": ["A"]
    },
    {
      "id": 15,
      "question": "一般商品包裝上都印製有條碼，台灣的國家代碼為下列哪一項？",
      "options": {
        "A": "471",
        "B": "886",
        "C": "957",
        "D": "977"
      },
      "answers": ["A"]
    },
    {
      "id": 16,
      "question": "下列哪一種記憶體較適合存放感測器電路系統中，所需要的程式或運算指令？",
      "options": {
        "A": "Flash ROM",
        "B": "DRAM",
        "C": "SRAM",
        "D": "Disk"
      },
      "answers": ["A"]
    },
    {
      "id": 17,
      "question": "關於 NFC 無線通訊技術，下列敘述哪一項錯誤？",
      "options": {
        "A": "適合一對多的多點通訊模式",
        "B": "適合手機行動支付",
        "C": "適合電子錢包儲值",
        "D": "安全性佳"
      },
      "answers": ["A"]
    },
    {
      "id": 18,
      "question": "NFC 設備可以在主動或被動模式下交換數據，下列哪一項通訊模式啟動查詢設備以提供整個射頻場域（RF-field）？",
      "options": {
        "A": "被動模式",
        "B": "半被動模式",
        "C": "主動模式",
        "D": "半主動模式"
      },
      "answers": ["C"]
    },
    {
      "id": 19,
      "question": "下列哪一種微處理器為目前感測器暨嵌入式系統的主流？",
      "options": {
        "A": "特殊應用積體電路（ASIC）",
        "B": "數位訊號處理器（DSP）",
        "C": "現場可程式化邏輯閘陣列（FPGA）",
        "D": "微控制器（MCU）"
      },
      "answers": ["D"]
    },
    {
      "id": 20,
      "question": "下列哪一種語言適合於開發無線感測電路之程式？",
      "options": {
        "A": "nesC",
        "B": "Turbo-C",
        "C": "Visual C++",
        "D": "Dev-C++"
      },
      "answers": ["A"]
    },
    {
      "id": 21,
      "question": "感測器為整合不同的硬體模組，模組間必須透過傳輸介面才得以成功交換資料，下列哪些為常見的溝通介面？",
      "options": {
        "A": "UART",
        "B": "SPI",
        "C": "I2C",
        "D": "JTAG"
      },
      "answers": ["A", "B", "C"]
    },
    {
      "id": 22,
      "question": "下列哪些為條碼技術的優點？",
      "options": {
        "A": "可靠性高",
        "B": "成本低",
        "C": "自由度大",
        "D": "容錯率高"
      },
      "answers": ["A", "B", "C"]
    },
    {
      "id": 23,
      "question": "應用於感測電路之微處理器種類中，除微控制器外尚有下列哪些？",
      "options": {
        "A": "特殊應用積體電路（ASIC）",
        "B": "數位訊號處理器（DSP）",
        "C": "現場可程式化邏輯閘陣列（FPGA）",
        "D": "中央處理器（CPU）"
      },
      "answers": ["A", "B", "C"]
    },
    {
      "id": 24,
      "question": "NFC 近場通訊在主動模式下，傳輸距離應為下列哪一項？",
      "options": {
        "A": "10 公分",
        "B": "10 英吋",
        "C": "20 公分",
        "D": "20 英吋"
      },
      "answers": ["C"]
    },
    {
      "id": 25,
      "question": "RFID 的通訊原理是依據電場和磁場的變化來產生電能，可分為電磁感應以及下列哪一項？",
      "options": {
        "A": "微波共振",
        "B": "核磁共振",
        "C": "電子共振",
        "D": "原子共振"
      },
      "answers": ["A"]
    },
    {
      "id": 26,
      "question": "在 NFC 的技術中，下列哪一項為主要的調變方式？",
      "options": {
        "A": "ASK",
        "B": "BSK",
        "C": "FSK",
        "D": "CDMA"
      },
      "answers": ["A"]
    },
    {
      "id": 27,
      "question": "於感測電路系統中，常見的無線通訊模組除 IrDA 外尚有下列哪些？",
      "options": {
        "A": "ZigBee",
        "B": "Bluetooth",
        "C": "Wi-Fi",
        "D": "UART"
      },
      "answers": ["A", "B", "C"]
    },
    {
      "id": 28,
      "question": "下列哪一種感測器是利用都卜勒效應（Doppler Effect）的原理而設計出來的？",
      "options": {
        "A": "電子羅盤",
        "B": "陀螺儀",
        "C": "移動偵測器",
        "D": "震動感測器"
      },
      "answers": ["C"]
    },
    {
      "id": 29,
      "question": "為使智慧型感測器能長期穩定工作，電源模組必須具備下列哪些特性？",
      "options": {
        "A": "低自放電（Low self-discharge）",
        "B": "高蓄電容量（High capacity/volume）",
        "C": "較短的充電時間（Shorter recharge time）",
        "D": "高電流下有效率地充電（Efficient recharging at high current）"
      },
      "answers": ["A", "B", "C"]
    },
    {
      "id": 30,
      "question": "下列哪一項裝置能夠探測外界訊號及物理條件（光、熱、溼度），並將探測之資訊傳給其他裝置？",
      "options": {
        "A": "感測器",
        "B": "微控制器",
        "C": "數位訊號處理器",
        "D": "特殊應用積體電路"
      },
      "answers": ["A"]
    },
    {
      "id": 31,
      "question": "下列哪一項專為無線感測電路所開發出來的嵌入式作業系統？",
      "options": {
        "A": "TinyOS",
        "B": "Linux",
        "C": "Unix",
        "D": "OS2"
      },
      "answers": ["A"]
    },
    {
      "id": 32,
      "question": "下列哪一項不屬於 RFID 讀取器內之主要元件？",
      "options": {
        "A": "收發器",
        "B": "微控制器",
        "C": "通訊介面",
        "D": "電子標籤"
      },
      "answers": ["D"]
    },
    {
      "id": 33,
      "question": "NFC 的通訊原理與下列哪一項技術原理相似？",
      "options": {
        "A": "RFID",
        "B": "Bar Code",
        "C": "QR Code",
        "D": "Bluetooth"
      },
      "answers": ["A"]
    },
    {
      "id": 34,
      "question": "QR Code 最早被日本應用於下列哪一種產業？",
      "options": {
        "A": "汽車業",
        "B": "食品業",
        "C": "家電業",
        "D": "電子業"
      },
      "answers": ["A"]
    },
    {
      "id": 35,
      "question": "大家常在各大百貨超級市場物品包裝上看到的條碼，最早成功應用於下列哪一種美國產業？",
      "options": {
        "A": "食品業",
        "B": "家電業",
        "C": "運輸業",
        "D": "成衣業"
      },
      "answers": ["A"]
    },
    {
      "id": 36,
      "question": "下列哪一項不屬於近距離無線通訊技術傳輸？",
      "options": {
        "A": "LTE",
        "B": "ZigBee",
        "C": "NFC",
        "D": "Bluetooth"
      },
      "answers": ["A"]
    },
    {
      "id": 37,
      "question": "NFC 設備為了能支援所有的系統，設備處於查詢狀態時，NFC 設備應先發出請求訊號，試探目標設備是否符合 NFC 標準，其所探詢的 NFC 標準應為下列哪些？",
      "options": {
        "A": "NFC-A",
        "B": "NFC-B",
        "C": "NFC-F",
        "D": "NFC-C"
      },
      "answers": ["A", "B", "C"]
    },
    {
      "id": 38,
      "question": "下列哪一種微處理器是指依特定用途而設計，它相當省電，因此適用於特殊需求的感測器電路系統中？",
      "options": {
        "A": "特殊應用積體電路（ASIC）",
        "B": "數位訊號處理器（DSP）",
        "C": "現場可程式化邏輯閘陣列（FPGA）",
        "D": "微控制器（MCU）"
      },
      "answers": ["A"]
    },
    {
      "id": 39,
      "question": "RFID 系統主要是由電子標籤、天線、應用系統以及下列哪一項元件所組成？",
      "options": {
        "A": "讀取器",
        "B": "應答器",
        "C": "收發器",
        "D": "感應器"
      },
      "answers": ["A"]
    },
    {
      "id": 40,
      "question": "根據 2004 年 NFC 論壇所定義的 NFCIP-2 標準，其工作頻率應為下列哪一項？",
      "options": {
        "A": "13.56MHz",
        "B": "125KHz",
        "C": "2.4GHz",
        "D": "5.8GHz"
      },
      "answers": ["A"]
    },
    {
      "id": 41,
      "question": "感測器的作用是將一種能量轉換成另一種能量形式，故有不少學者稱它為下列哪一種名稱？",
      "options": {
        "A": "Transducer",
        "B": "Transmitter",
        "C": "Receiver",
        "D": "Converter"
      },
      "answers": ["A"]
    },
    {
      "id": 42,
      "question": "NFC 的應用可以歸類成四種情境，下列哪一項較適合用於行動支付？",
      "options": {
        "A": "碰一下就好（Touch and Go）",
        "B": "碰一下再確認（Touch and Confirm）",
        "C": "碰一下再溝通（Touch and Connect）",
        "D": "碰一下就上網（Touch and Explore）"
      },
      "answers": ["B"]
    },
    {
      "id": 43,
      "question": "主動式 RFID 標籤由下列哪些元件所組成？",
      "options": {
        "A": "天線",
        "B": "晶片",
        "C": "電池",
        "D": "讀取器"
      },
      "answers": ["A", "B", "C"]
    },
    {
      "id": 44,
      "question": "關於 NFC 與藍芽（Bluetooth）的特性，下列敘述哪些正確？",
      "options": {
        "A": "NFC 的傳輸距離比藍芽近",
        "B": "NFC 的傳輸速率比藍芽慢",
        "C": "NFC 的程式初始化時間比藍芽慢",
        "D": "NFC 的傳輸距離比藍芽遠"
      },
      "answers": ["A", "B"]
    },
    {
      "id": 45,
      "question": "NFC 的訊息封包格式包含有 Header 與 Payload，而 Header 的內容又可分為下列哪三個部分？",
      "options": {
        "A": "Record 狀態",
        "B": "長度",
        "C": "型態",
        "D": "起始"
      },
      "answers": ["A", "B", "C"]
    },
    {
      "id": 46,
      "question": "當使用 NFC 技術傳遞資料訊息時，除了 NFC 裝置之間需先建立通訊連線外，還需要將資料訊息轉為下列哪一種格式傳送？",
      "options": {
        "A": "NDEF（NFC dataExchange Formate）",
        "B": "PCD（Proximity Coupling Device Mode）",
        "C": "VCD（Vicinity Coupling Device Mode）",
        "D": "NRZ-L（Not Return to Zero-Low）"
      },
      "answers": ["A"]
    },
    {
      "id": 47,
      "question": "下列哪一項不屬於 RFID 晶片內之元件？",
      "options": {
        "A": "天線",
        "B": "記憶體",
        "C": "邏輯單元",
        "D": "電源控制器"
      },
      "answers": ["A"]
    },
    {
      "id": 48,
      "question": "下列哪一種電源模組體積小、放電穩定且可長時間保存，但缺點是含有重金屬汞且價格高？",
      "options": {
        "A": "水銀電池",
        "B": "鎳氫電池",
        "C": "鋰電池",
        "D": "鉛酸電池"
      },
      "answers": ["A"]
    },
    {
      "id": 49,
      "question": "欲完成一件完整之感測工作，除感測元件及電源供應外，尚需下列哪些模組？",
      "options": {
        "A": "記憶體",
        "B": "通訊模組",
        "C": "微處理器",
        "D": "網路模組"
      },
      "answers": ["A", "B", "C"]
    },
    {
      "id": 50,
      "question": "目前國際商品條碼 GS1 主要由下列哪兩大系統整合而成？",
      "options": {
        "A": "通用產品代碼（UPC）",
        "B": "歐洲商品條碼（EAN）",
        "C": "美國統一編碼協會（UCC）",
        "D": "食品工業統一碼（UGPIC）"
      },
      "answers": ["B", "C"]
    }
  ]
}